leonardo_ai_sdk/__init__.py
leonardo_ai_sdk/_hooks/__init__.py
leonardo_ai_sdk/_hooks/sdkhooks.py
leonardo_ai_sdk/_hooks/types.py
leonardo_ai_sdk/_version.py
leonardo_ai_sdk/basesdk.py
leonardo_ai_sdk/dataset.py
leonardo_ai_sdk/elements.py
leonardo_ai_sdk/httpclient.py
leonardo_ai_sdk/image.py
leonardo_ai_sdk/init_images.py
leonardo_ai_sdk/models/errors/__init__.py
leonardo_ai_sdk/models/errors/sdkerror.py
leonardo_ai_sdk/models/operations/__init__.py
leonardo_ai_sdk/models/operations/createdataset.py
leonardo_ai_sdk/models/operations/createelement.py
leonardo_ai_sdk/models/operations/creategeneration.py
leonardo_ai_sdk/models/operations/createlcmgeneration.py
leonardo_ai_sdk/models/operations/createmodel.py
leonardo_ai_sdk/models/operations/createsvdmotiongeneration.py
leonardo_ai_sdk/models/operations/createtexturegeneration.py
leonardo_ai_sdk/models/operations/createuniversalupscalerjob.py
leonardo_ai_sdk/models/operations/createvariationnobg.py
leonardo_ai_sdk/models/operations/createvariationunzoom.py
leonardo_ai_sdk/models/operations/createvariationupscale.py
leonardo_ai_sdk/models/operations/delete3dmodelbyid.py
leonardo_ai_sdk/models/operations/deletedatasetbyid.py
leonardo_ai_sdk/models/operations/deleteelementbyid.py
leonardo_ai_sdk/models/operations/deletegenerationbyid.py
leonardo_ai_sdk/models/operations/deleteinitimagebyid.py
leonardo_ai_sdk/models/operations/deletemodelbyid.py
leonardo_ai_sdk/models/operations/deletetexturegenerationbyid.py
leonardo_ai_sdk/models/operations/get3dmodelbyid.py
leonardo_ai_sdk/models/operations/get3dmodelsbyuserid.py
leonardo_ai_sdk/models/operations/getcustomelementsbyuserid.py
leonardo_ai_sdk/models/operations/getcustommodelsbyuserid.py
leonardo_ai_sdk/models/operations/getdatasetbyid.py
leonardo_ai_sdk/models/operations/getelementbyid.py
leonardo_ai_sdk/models/operations/getgenerationbyid.py
leonardo_ai_sdk/models/operations/getgenerationsbyuserid.py
leonardo_ai_sdk/models/operations/getinitimagebyid.py
leonardo_ai_sdk-6.4.0.dist-info/LICENSE.md
leonardo_ai_sdk-6.4.0.dist-info/METADATA
leonardo_ai_sdk-6.4.0.dist-info/WHEEL
leonardo_ai_sdk-6.4.0.dist-info/RECORD
